{"version":1,"resource":"vscode-remote://wsl%2Bubuntu/home/senac/meu-app-react/src/index.js","entries":[{"id":"x1sB.js","timestamp":1665701581721},{"id":"V9Od.js","timestamp":1665701726231},{"id":"uxTH.js","timestamp":1665704650801},{"id":"s3EH.js","timestamp":1665705504851},{"id":"TVJl.js","timestamp":1665705899361},{"id":"Tz0u.js","timestamp":1665707004781},{"id":"TCzr.js","timestamp":1665707086081},{"id":"kelm.js","source":"Edição do Workspace","timestamp":1665707369431},{"id":"dhsr.js","timestamp":1665708532991},{"id":"zeIL.js","timestamp":1665708732511},{"id":"b68P.js","timestamp":1665708938601},{"id":"ck4d.js","timestamp":1665709192271},{"id":"BatZ.js","timestamp":1665786915582},{"id":"HY1E.js","timestamp":1665788679482},{"id":"RrxS.js","timestamp":1665788824812},{"id":"xtTN.js","timestamp":1665789110602}]}